mateco/__init__.py
mateco/mateco.py
mateco-1.4.1.dist-info/LICENSE
mateco-1.4.1.dist-info/WHEEL
mateco-1.4.1.dist-info/METADATA
mateco-1.4.1.dist-info/RECORD
