Metadata-Version: 2.1
Name: mateco
Version: 1.4.1
Summary: Master Text Converter
Home-page: https://github.com/tquangsdh20/mateco
License: MIT
Author: Joseph Quang
Author-email: tquangsdh20@fsob.win
Requires-Python: >=3.6,<4.0
Classifier: Development Status :: 5 - Production/Stable
Classifier: Intended Audience :: Education
Classifier: Intended Audience :: End Users/Desktop
Classifier: License :: OSI Approved :: MIT License
Classifier: Operating System :: OS Independent
Classifier: Programming Language :: Python :: 3
Classifier: Programming Language :: Python :: 3.10
Classifier: Programming Language :: Python :: 3.6
Classifier: Programming Language :: Python :: 3.7
Classifier: Programming Language :: Python :: 3.8
Classifier: Programming Language :: Python :: 3.9
Requires-Dist: playsound (==1.2.2)
Requires-Dist: pyfreetts (>=0.1,<0.2)
Requires-Dist: text2ipa (>=1.4,<2.0)
Project-URL: Repository, https://github.com/tquangsdh20/mateco
